hatch_min_requirements/__init__.py
hatch_min_requirements/_fetch.py
hatch_min_requirements/py.typed
hatch_min_requirements/util.py
hatch_min_requirements-0.2.0.dist-info/METADATA
hatch_min_requirements-0.2.0.dist-info/WHEEL
hatch_min_requirements-0.2.0.dist-info/entry_points.txt
hatch_min_requirements-0.2.0.dist-info/licenses/LICENSE
hatch_min_requirements-0.2.0.dist-info/RECORD
